vfflags/__init__.py
vfflags/py.typed
vf_flags-0.2.4.dist-info/LICENSE
vf_flags-0.2.4.dist-info/METADATA
vf_flags-0.2.4.dist-info/WHEEL
vf_flags-0.2.4.dist-info/top_level.txt
vf_flags-0.2.4.dist-info/RECORD
